pyunit_color/__init__.py
pyunit_color/color.py
pyunit_color-2020.2.11.dist-info/METADATA
pyunit_color-2020.2.11.dist-info/WHEEL
pyunit_color-2020.2.11.dist-info/top_level.txt
pyunit_color-2020.2.11.dist-info/zip-safe
pyunit_color-2020.2.11.dist-info/RECORD
