Metadata-Version: 2.1
Name: pyunit-color
Version: 2020.2.11
Summary: 控制台打印颜色信息
Home-page: https://github.com/PyUnit/pyunit-color
Author: Jtyoui
Author-email: jtyoui@qq.com
License: MIT Licence
Platform: any
Classifier: Programming Language :: Python :: 3
Classifier: License :: OSI Approved :: MIT License
Classifier: Operating System :: OS Independent
Requires-Dist: colorama (==0.4.3)
